{
  "type": "pfm:furniture",
  "group": "kitchen",
  "ingredients": [
    {
      "item": "quark:jasper"
    },
    {
      "item": "quark:jasper"
    },
    {
      "item": "quark:jasper"
    },
    {
      "item": "quark:jasper"
    },
    {
      "item": "quark:jasper"
    },
    {
      "item": "quark:polished_jasper"
    },
    {
      "item": "quark:polished_jasper"
    },
    {
      "item": "quark:polished_jasper"
    },
    {
      "item": "minecraft:furnace"
    }
  ],
  "result": {
    "item": "pfm:jasper_quark_kitchen_counter_oven"
  }
}