{
  "parent": "minecraft:recipes/root",
  "criteria": {
    "has_the_recipe": {
      "conditions": {
        "recipe": "pfm:myalite_quark_coffee_table_basic"
      },
      "trigger": "minecraft:recipe_unlocked"
    },
    "myalite_quark_coffee_table_basic": {
      "conditions": {
        "items": [
          {
            "items": [
              "quark:polished_myalite"
            ]
          }
        ]
      },
      "trigger": "minecraft:inventory_changed"
    }
  },
  "requirements": [
    [
      "myalite_quark_coffee_table_basic",
      "has_the_recipe"
    ]
  ],
  "rewards": {
    "recipes": [
      "pfm:myalite_quark_coffee_table_basic"
    ]
  },
  "sends_telemetry_event": true
}